LICENSE
MANIFEST.in
README.rst
requirements-docs.txt
requirements-extra-cli.txt
requirements-test.txt
requirements.txt
setup.cfg
setup.py
tox.ini
storj/__init__.py
storj/api.py
storj/configuration.py
storj/downloader.py
storj/exception.py
storj/file_crypto.py
storj/http.py
storj/metadata.py
storj/model.py
storj/sharder.py
storj/uploader.py
storj/web_socket.py
storj.egg-info/PKG-INFO
storj.egg-info/SOURCES.txt
storj.egg-info/dependency_links.txt
storj.egg-info/entry_points.txt
storj.egg-info/requires.txt
storj.egg-info/top_level.txt
storj/cli/__init__.py
tests/__init__.py
tests/config.py
tests/log_config.py
tests/logging.conf
tests/storj.cfg
tests/integration/__init__.py
tests/integration/bucket_test.py
tests/unit/__init__.py
tests/unit/api_test.py
tests/unit/cli_test.py
tests/unit/configuration_test.py
tests/unit/exception_test.py
tests/unit/http_test.py
tests/unit/model_test.py
tests/unit/storj_test.py