Metadata-Version: 1.1
Name: storj
Version: 0.3.4
Summary: A Python SDK for the Storj API
Home-page: http://storj.io
Author: Daniel Hawkins, Fabian Barkhau, James Prestwich, Marc Schubert, Marco Rosa, Mike Bailey, Pedro Salgado, Shawn Wilkinson, Wiktor Jezioro
Author-email: hwkns@alum.mit.edu;f483@storj.io;james@storj.io;marc.schubert@gmail.com;marcor165@hotmail.it;mibgranny@aol.com;steenzout@ymail.com;shawn+pythonsdk@storj.io;lakewik@lakewik.pl
License: MIT
Keywords: storj,bridge,metadisk,api,client,sdk,python
Platform: UNKNOWN
Classifier: Development Status :: 4 - Beta
Classifier: Intended Audience :: Developers
Classifier: License :: OSI Approved :: MIT License
Classifier: Operating System :: OS Independent
Classifier: Programming Language :: Python
Classifier: Programming Language :: Python :: 2
Classifier: Programming Language :: Python :: 2.7
Classifier: Programming Language :: Python :: Implementation :: CPython
Classifier: Programming Language :: Python :: Implementation :: PyPy
Classifier: Topic :: Internet :: WWW/HTTP
